particletools/ParticleData.xml
particletools/__init__.py
particletools/tables.py
particletools-1.1.7.dist-info/LICENSE
particletools-1.1.7.dist-info/METADATA
particletools-1.1.7.dist-info/WHEEL
particletools-1.1.7.dist-info/top_level.txt
particletools-1.1.7.dist-info/RECORD
