Metadata-Version: 2.1
Name: particletools
Version: 1.1.7
Summary: Translating particle codes from CR models from/to PDG codes
Home-page: https://github.com/afedynitch/particletools
Author: Anatoli Fedynitch
Author-email: afedynitch@gmail.com
License: MIT
Classifier: Programming Language :: Python
Classifier: Programming Language :: Python :: 2
Classifier: Programming Language :: Python :: 2.7
Classifier: Programming Language :: Python :: 3
Classifier: Programming Language :: Python :: 3.6
Classifier: Programming Language :: Python :: 3.7
Classifier: Programming Language :: Python :: 3.8
Classifier: Topic :: Scientific/Engineering :: Physics
Classifier: Intended Audience :: Science/Research
Classifier: Development Status :: 5 - Production/Stable
Classifier: License :: OSI Approved :: MIT License
License-File: LICENSE
